README.rst
setup.cfg
setup.py
wcag_zoo/__init__.py
wcag_zoo/testrunner.py
wcag_zoo/utils.py
wcag_zoo/zookeeper.py
wcag_zoo.egg-info/PKG-INFO
wcag_zoo.egg-info/SOURCES.txt
wcag_zoo.egg-info/dependency_links.txt
wcag_zoo.egg-info/entry_points.txt
wcag_zoo.egg-info/requires.txt
wcag_zoo.egg-info/top_level.txt
wcag_zoo/validators/__init__.py
wcag_zoo/validators/anteater.py
wcag_zoo/validators/ayeaye.py
wcag_zoo/validators/glowworm.py
wcag_zoo/validators/molerat.py
wcag_zoo/validators/parade.py
wcag_zoo/validators/tarsier.py