Metadata-Version: 1.1
Name: wcag-zoo
Version: 0.2.4
Summary: UNKNOWN
Home-page: https://github.com/data61/wcag-zoo
Author: Samuel Spencer
Author-email: sam@aristotlemetadata.com
License: UNKNOWN
Platform: UNKNOWN
Classifier: Development Status :: 5 - Production/Stable
Classifier: Environment :: Web Environment
Classifier: Intended Audience :: Information Technology
Classifier: Intended Audience :: Science/Research
Classifier: Operating System :: OS Independent
Classifier: Programming Language :: Python :: 3 :: Only
